LICENSE.txt
README.md
setup.py
src/expfig/__init__.py
src/expfig/fig.py
src/expfig/namespacify.py
src/expfig.egg-info/PKG-INFO
src/expfig.egg-info/SOURCES.txt
src/expfig.egg-info/dependency_links.txt
src/expfig.egg-info/requires.txt
src/expfig.egg-info/top_level.txt