Metadata-Version: 2.1
Name: expfig
Version: 0.1
Summary: A yaml-based configuration for reproducible python experiments.
Home-page: UNKNOWN
Maintainer: Avishai Halev
Maintainer-email: avishaihalev@gmail.com
License: MIT License
Platform: UNKNOWN
Requires-Python: >=3.6
License-File: LICENSE.txt
